humancat/__init__.py
humancat/cat.py
humancat/human.py
humancat-0.0.5.dist-info/METADATA
humancat-0.0.5.dist-info/WHEEL
humancat-0.0.5.dist-info/top_level.txt
humancat-0.0.5.dist-info/RECORD
