Metadata-Version: 2.1
Name: humancat
Version: 0.0.5
Summary: GitHub Action Build Test Sample
Home-page: https://github.com/jihyungSong/github-action-course
Author: jihyungSong
Author-email: bluese05@gmail.com
License: UNKNOWN
Keywords: sample,cat,human,humancat
Platform: UNKNOWN
Requires-Python: >=3.8
